flock_flightplan/__init__.py
flock_flightplan/app.py
flock_flightplan/project_tree.py
flock_flightplan/utils.py
flock_flightplan/agents/flocky.py
flock_flightplan/agents/planning.py
flock_flightplan-0.1.1.dist-info/METADATA
flock_flightplan-0.1.1.dist-info/WHEEL
flock_flightplan-0.1.1.dist-info/entry_points.txt
flock_flightplan-0.1.1.dist-info/RECORD
