Metadata-Version: 2.4
Name: flock-flightplan
Version: 0.1.1
Summary: Add your description here
Requires-Python: >=3.10
Requires-Dist: flock-core>=0.4.0b20
Requires-Dist: httpx>=0.26.0
Requires-Dist: textual-dev>=1.7.0
Requires-Dist: textual-web>=0.4.2
Requires-Dist: textual>=3.1.0
